{
  "timestamp": 1691255653,
  "totalData": {
    "totalDistance": 56.46606,
    "totalHours": 8.76361111111111,
    "totalPoints": 1.4242579107468125
  },
  "summary": [
    {
      "name": "Nordic Semiconductor - Finland",
      "distance": 3.43816,
      "hours": 0.029840277777777775,
      "clubPoints": 0.042977,
      "elevation": 158
    },
    {
      "name": "Nordic Semiconductor - Poland",
      "distance": 0,
      "hours": 0,
      "clubPoints": 0,
      "elevation": 0
    },
    {
      "name": "Nordic Semiconductor - Europe",
      "distance": 0,
      "hours": 0,
      "clubPoints": 0,
      "elevation": 0
    },
    {
      "name": "Nordic Semiconductor - APAC",
      "distance": 0,
      "hours": 0,
      "clubPoints": 0,
      "elevation": 0
    },
    {
      "name": "Nordic Semiconductor - USA",
      "distance": 25.3566,
      "hours": 0.12269444444444444,
      "clubPoints": 1.26783,
      "elevation": 472.7
    },
    {
      "name": "Nordic Semiconductor - Trondheim Office",
      "distance": 11.7935,
      "hours": 0.012627504553734063,
      "clubPoints": 0.06444535519125683,
      "elevation": 367.4
    },
    {
      "name": "Omega NTNU",
      "distance": 15.877799999999999,
      "hours": 0.004974279835390947,
      "clubPoints": 0.04900555555555555,
      "elevation": 144
    },
    {
      "name": "Nordic Semiconductor - Oslo Office",
      "distance": 0,
      "hours": 0,
      "clubPoints": 0,
      "elevation": 0
    }
  ]
}