{
  "timestamp": 1687252655,
  "totalData": {
    "totalDistance": 582.7818666666668,
    "totalHours": 115.14916666666667,
    "totalPoints": 6.494636984593839
  },
  "summary": [
    {
      "name": "Nordic Semiconductor - Finland",
      "distance": 122.27420000000001,
      "hours": 0.2865625,
      "clubPoints": 1.5284275,
      "elevation": 1538.5
    },
    {
      "name": "Nordic Semiconductor - Poland",
      "distance": 45.1558,
      "hours": 0.7489980158730158,
      "clubPoints": 1.612707142857143,
      "elevation": 462.8
    },
    {
      "name": "Nordic Semiconductor - Europe",
      "distance": 33.57703333333333,
      "hours": 0.37172431865828093,
      "clubPoints": 0.6335289308176101,
      "elevation": 530.4000000000001
    },
    {
      "name": "Nordic Semiconductor - APAC",
      "distance": 26.358400000000003,
      "hours": 0.07319097222222222,
      "clubPoints": 0.32948,
      "elevation": 195.4
    },
    {
      "name": "Nordic Semiconductor - USA",
      "distance": 14.1375,
      "hours": 0.08195833333333333,
      "clubPoints": 0.7068749999999999,
      "elevation": 157.4
    },
    {
      "name": "Nordic Semiconductor - Trondheim Office",
      "distance": 125.3845,
      "hours": 0.09730115361262903,
      "clubPoints": 0.6851612021857922,
      "elevation": 2784.1000000000004
    },
    {
      "name": "Omega NTNU",
      "distance": 182.70310000000003,
      "hours": 0.05674948240165631,
      "clubPoints": 0.5674009316770187,
      "elevation": 2103.3
    },
    {
      "name": "Nordic Semiconductor - Oslo Office",
      "distance": 33.191333333333326,
      "hours": 0.10359668109668108,
      "clubPoints": 0.43105627705627697,
      "elevation": 452.79999999999995
    }
  ]
}