{
  "timestamp": 1665613740,
  "totalData": {
    "totalDistance": 1550.4577133333335,
    "totalHours": 242.97500000000005,
    "totalPoints": 19.814198137987546
  },
  "summary": [
    {
      "name": "Nordic Semiconductor - Finland",
      "distance": 321.36856666666665,
      "hours": 0.8916435185185184,
      "clubPoints": 4.463452314814814,
      "elevation": 2856.7999999999997
    },
    {
      "name": "Nordic Semiconductor - Poland",
      "distance": 122.3926,
      "hours": 0.6978174603174602,
      "clubPoints": 4.371164285714285,
      "elevation": 1971.3
    },
    {
      "name": "Nordic Semiconductor - Europe",
      "distance": 72.71686666666668,
      "hours": 0.2501199494949495,
      "clubPoints": 1.6526560606060605,
      "elevation": 879
    },
    {
      "name": "Nordic Semiconductor - APAC",
      "distance": 117.35349999999998,
      "hours": 0.26225308641975315,
      "clubPoints": 1.629909722222222,
      "elevation": 1688.7000000000003
    },
    {
      "name": "Nordic Semiconductor - USA",
      "distance": 65.733,
      "hours": 0.7852513227513226,
      "clubPoints": 3.130142857142858,
      "elevation": 853.5
    },
    {
      "name": "Nordic Semiconductor - Trondheim Office",
      "distance": 240.99856666666665,
      "hours": 0.20781127704204633,
      "clubPoints": 1.4321168897341974,
      "elevation": 3824.2000000000003
    },
    {
      "name": "Omega NTNU",
      "distance": 496.0919,
      "hours": 0.17453434982155935,
      "clubPoints": 1.6942153326476224,
      "elevation": 5388.700000000001
    },
    {
      "name": "Nordic Semiconductor - Oslo Office",
      "distance": 113.80271333333332,
      "hours": 0.3390189873417722,
      "clubPoints": 1.4405406751054854,
      "elevation": 2370.2
    }
  ]
}