{
  "timestamp": 1676038755,
  "totalData": {
    "totalDistance": 1335.0961000000002,
    "totalHours": 654.6788888888888,
    "totalPoints": 17.495183628479023
  },
  "summary": [
    {
      "name": "Nordic Semiconductor - Finland",
      "distance": 283.4668333333334,
      "hours": 0.7447769953051644,
      "clubPoints": 3.9924906103286393,
      "elevation": 5303.900000000001
    },
    {
      "name": "Nordic Semiconductor - Poland",
      "distance": 52.1722,
      "hours": 1.080625,
      "clubPoints": 1.8632928571428573,
      "elevation": 443.4
    },
    {
      "name": "Nordic Semiconductor - Europe",
      "distance": 93.94733333333333,
      "hours": 0.25307328605200946,
      "clubPoints": 1.9988794326241135,
      "elevation": 711.4
    },
    {
      "name": "Nordic Semiconductor - APAC",
      "distance": 68.61713333333333,
      "hours": 0.1422417840375587,
      "clubPoints": 0.9664384976525822,
      "elevation": 689.3
    },
    {
      "name": "Nordic Semiconductor - USA",
      "distance": 99.3682,
      "hours": 3.342458333333334,
      "clubPoints": 4.9684099999999995,
      "elevation": 13859.1
    },
    {
      "name": "Nordic Semiconductor - Trondheim Office",
      "distance": 166.27966666666666,
      "hours": 0.19091387245233396,
      "clubPoints": 0.983903353057199,
      "elevation": 2465.3
    },
    {
      "name": "Omega NTNU",
      "distance": 492.60169999999994,
      "hours": 1.4914659436834092,
      "clubPoints": 1.686992123287671,
      "elevation": 5503.900000000001
    },
    {
      "name": "Nordic Semiconductor - Oslo Office",
      "distance": 78.64303333333332,
      "hours": 0.19640716374269007,
      "clubPoints": 1.034776754385965,
      "elevation": 787.2
    }
  ]
}