{
  "timestamp": 1671121813,
  "totalData": {
    "totalDistance": 874.4258,
    "totalHours": 134.1905555555555,
    "totalPoints": 11.825084691605143
  },
  "summary": [
    {
      "name": "Nordic Semiconductor - Finland",
      "distance": 141.95666666666668,
      "hours": 0.39332947530864204,
      "clubPoints": 1.9716203703703705,
      "elevation": 2190.8
    },
    {
      "name": "Nordic Semiconductor - Poland",
      "distance": 76.37346666666667,
      "hours": 0.4755651340996168,
      "clubPoints": 2.6335678160919542,
      "elevation": 475.3
    },
    {
      "name": "Nordic Semiconductor - Europe",
      "distance": 70.92486666666666,
      "hours": 0.2208564814814815,
      "clubPoints": 1.4776013888888886,
      "elevation": 752.2
    },
    {
      "name": "Nordic Semiconductor - APAC",
      "distance": 36.5222,
      "hours": 0.06114197530864198,
      "clubPoints": 0.5072527777777778,
      "elevation": 287.5
    },
    {
      "name": "Nordic Semiconductor - USA",
      "distance": 55.23459999999999,
      "hours": 0.48593915343915345,
      "clubPoints": 2.6302190476190477,
      "elevation": 575.5999999999999
    },
    {
      "name": "Nordic Semiconductor - Trondheim Office",
      "distance": 139.0415666666667,
      "hours": 0.12959477124183008,
      "clubPoints": 0.8178915686274509,
      "elevation": 1935.6
    },
    {
      "name": "Omega NTNU",
      "distance": 294.77849999999995,
      "hours": 0.11164662084765178,
      "clubPoints": 1.012984536082474,
      "elevation": 3621.4
    },
    {
      "name": "Nordic Semiconductor - Oslo Office",
      "distance": 59.59393333333333,
      "hours": 0.16040404040404038,
      "clubPoints": 0.7739471861471862,
      "elevation": 1092.6999999999998
    }
  ]
}