{
  "timestamp": 1694265471,
  "totalData": {
    "totalDistance": 2542.83244,
    "totalHours": 498.4761111111112,
    "totalPoints": 35.43365413827489
  },
  "summary": [
    {
      "name": "Nordic Semiconductor - Finland",
      "distance": 550.8018133333333,
      "hours": 1.094409722222222,
      "clubPoints": 6.885022666666669,
      "elevation": 9030.1
    },
    {
      "name": "Nordic Semiconductor - Poland",
      "distance": 315.62723333333344,
      "hours": 3.913353174603175,
      "clubPoints": 11.272401190476188,
      "elevation": 5563.799999999999
    },
    {
      "name": "Nordic Semiconductor - Europe",
      "distance": 157.98336666666665,
      "hours": 1.202714884696017,
      "clubPoints": 2.98081823899371,
      "elevation": 2766.5
    },
    {
      "name": "Nordic Semiconductor - APAC",
      "distance": 95.5884,
      "hours": 0.15252430555555554,
      "clubPoints": 1.194855,
      "elevation": 525.4000000000001
    },
    {
      "name": "Nordic Semiconductor - USA",
      "distance": 132.5506,
      "hours": 0.958888888888889,
      "clubPoints": 6.62753,
      "elevation": 2040.8
    },
    {
      "name": "Nordic Semiconductor - Trondheim Office",
      "distance": 309.1083933333334,
      "hours": 0.4550880388585306,
      "clubPoints": 1.689116903460838,
      "elevation": 9054.699999999999
    },
    {
      "name": "Omega NTNU",
      "distance": 815.7405999999997,
      "hours": 0.26769118655692736,
      "clubPoints": 2.517717901234568,
      "elevation": 13196.700000000004
    },
    {
      "name": "Nordic Semiconductor - Oslo Office",
      "distance": 165.43203333333332,
      "hours": 0.4960654490106544,
      "clubPoints": 2.266192237442923,
      "elevation": 4267.5999999999985
    }
  ]
}