{
  "timestamp": 1674321395,
  "totalData": {
    "totalDistance": 1191852.0948333333,
    "totalHours": 240369.07527777774,
    "totalPoints": 21940.025509843326
  },
  "summary": [
    {
      "name": "Nordic Semiconductor - Finland",
      "distance": 190813.47899999993,
      "hours": 662.7281070139977,
      "clubPoints": 2664.4341029081943,
      "elevation": 6158045.299999984
    },
    {
      "name": "Nordic Semiconductor - Poland",
      "distance": 217433.7693333335,
      "hours": 1311.6537558155462,
      "clubPoints": 7621.01827906404,
      "elevation": 2838895.5999999936
    },
    {
      "name": "Nordic Semiconductor - Europe",
      "distance": 189914.5378666667,
      "hours": 663.89215659476,
      "clubPoints": 3997.834509633578,
      "elevation": 2636111.399999992
    },
    {
      "name": "Nordic Semiconductor - APAC",
      "distance": 92412.3163000003,
      "hours": 246.2797410776385,
      "clubPoints": 1292.3510736502335,
      "elevation": 1151936.8000000014
    },
    {
      "name": "Nordic Semiconductor - USA",
      "distance": 60224.100366666746,
      "hours": 816.3831937830707,
      "clubPoints": 2937.0018169841273,
      "elevation": 1422549.5999999973
    },
    {
      "name": "Nordic Semiconductor - Trondheim Office",
      "distance": 143648.29849999992,
      "hours": 189.26326976253986,
      "clubPoints": 846.9955040445533,
      "elevation": 3502220.9000000036
    },
    {
      "name": "Omega NTNU",
      "distance": 135456.82520000022,
      "hours": 50.522842688048904,
      "clubPoints": 465.4873718213057,
      "elevation": 1089492
    },
    {
      "name": "Nordic Semiconductor - Oslo Office",
      "distance": 161948.76826666686,
      "hours": 559.0630750170887,
      "clubPoints": 2114.9028517372976,
      "elevation": 3189767.999999992
    }
  ]
}