{
  "timestamp": 1682029070,
  "totalData": {
    "totalDistance": 3103.74816,
    "totalHours": 481.80444444444447,
    "totalPoints": 34.03714581819049
  },
  "summary": [
    {
      "name": "Nordic Semiconductor - Finland",
      "distance": 444.50230000000005,
      "hours": 0.981273823998361,
      "clubPoints": 5.555114059577256,
      "elevation": 6936.100000000003
    },
    {
      "name": "Nordic Semiconductor - Poland",
      "distance": 177.9529333333334,
      "hours": 1.134920634920635,
      "clubPoints": 6.355461904761904,
      "elevation": 2417
    },
    {
      "name": "Nordic Semiconductor - Europe",
      "distance": 206.10643333333334,
      "hours": 0.561846147263937,
      "clubPoints": 3.9742352586317535,
      "elevation": 3177.6
    },
    {
      "name": "Nordic Semiconductor - APAC",
      "distance": 178.27763333333334,
      "hours": 0.3755554157165023,
      "clubPoints": 2.2028566931971563,
      "elevation": 2235.5
    },
    {
      "name": "Nordic Semiconductor - USA",
      "distance": 99.21066666666667,
      "hours": 1.429375,
      "clubPoints": 4.960533333333332,
      "elevation": 5914.4
    },
    {
      "name": "Nordic Semiconductor - Trondheim Office",
      "distance": 738.0365999999998,
      "hours": 0.612113742925674,
      "clubPoints": 4.06218685283351,
      "elevation": 15577.7
    },
    {
      "name": "Omega NTNU",
      "distance": 960.7166000000001,
      "hours": 0.333466906417972,
      "clubPoints": 3.037269217336536,
      "elevation": 10126.999999999998
    },
    {
      "name": "Nordic Semiconductor - Oslo Office",
      "distance": 298.9449933333334,
      "hours": 0.8655280246069721,
      "clubPoints": 3.889488498519024,
      "elevation": 5344.6
    }
  ]
}