{
  "timestamp": 1679411826,
  "totalData": {
    "totalDistance": 522.3727333333333,
    "totalHours": 84.41583333333334,
    "totalPoints": 5.546030957453986
  },
  "summary": [
    {
      "name": "Nordic Semiconductor - Finland",
      "distance": 91.1403,
      "hours": 0.28176838810641625,
      "clubPoints": 1.2836661971830985,
      "elevation": 1342.2
    },
    {
      "name": "Nordic Semiconductor - Poland",
      "distance": 25.925933333333337,
      "hours": 0.21167658730158728,
      "clubPoints": 0.9259261904761905,
      "elevation": 381.8
    },
    {
      "name": "Nordic Semiconductor - Europe",
      "distance": 28.827033333333336,
      "hours": 0.06695626477541372,
      "clubPoints": 0.6133411347517731,
      "elevation": 282.40000000000003
    },
    {
      "name": "Nordic Semiconductor - APAC",
      "distance": 37.71553333333333,
      "hours": 0.12107589984350549,
      "clubPoints": 0.5312046948356808,
      "elevation": 179.3
    },
    {
      "name": "Nordic Semiconductor - USA",
      "distance": 14.678966666666666,
      "hours": 0.3374722222222222,
      "clubPoints": 0.7339483333333333,
      "elevation": 245
    },
    {
      "name": "Nordic Semiconductor - Trondheim Office",
      "distance": 101.34696666666667,
      "hours": 0.09215976331360946,
      "clubPoints": 0.5996861932938855,
      "elevation": 1350.3999999999999
    },
    {
      "name": "Omega NTNU",
      "distance": 212.6753,
      "hours": 0.07547686765263556,
      "clubPoints": 0.7258542662116041,
      "elevation": 1588.1
    },
    {
      "name": "Nordic Semiconductor - Oslo Office",
      "distance": 10.062700000000001,
      "hours": 0.030274122807017544,
      "clubPoints": 0.13240394736842107,
      "elevation": 188
    }
  ]
}