{
  "timestamp": 1691046963,
  "totalData": {
    "totalDistance": 1880.7386600000002,
    "totalHours": 296.1377777777778,
    "totalPoints": 23.516185937047027
  },
  "summary": [
    {
      "name": "Nordic Semiconductor - Finland",
      "distance": 342.25856000000005,
      "hours": 0.6231562500000002,
      "clubPoints": 4.278232000000001,
      "elevation": 5285.6
    },
    {
      "name": "Nordic Semiconductor - Poland",
      "distance": 162.55309999999997,
      "hours": 1.1112896825396823,
      "clubPoints": 5.805467857142857,
      "elevation": 2226.5
    },
    {
      "name": "Nordic Semiconductor - Europe",
      "distance": 68.7439,
      "hours": 0.1316090146750524,
      "clubPoints": 1.2970547169811324,
      "elevation": 418.40000000000003
    },
    {
      "name": "Nordic Semiconductor - APAC",
      "distance": 66.3722,
      "hours": 0.09719444444444443,
      "clubPoints": 0.8296525000000001,
      "elevation": 401.9
    },
    {
      "name": "Nordic Semiconductor - USA",
      "distance": 111.02770000000001,
      "hours": 0.9365694444444445,
      "clubPoints": 5.551385,
      "elevation": 1531.7
    },
    {
      "name": "Nordic Semiconductor - Trondheim Office",
      "distance": 380.32849999999996,
      "hours": 0.5092744383727991,
      "clubPoints": 2.0782978142076507,
      "elevation": 11568.5
    },
    {
      "name": "Omega NTNU",
      "distance": 617.9768,
      "hours": 0.19790466392318243,
      "clubPoints": 1.907335802469136,
      "elevation": 8797.100000000002
    },
    {
      "name": "Nordic Semiconductor - Oslo Office",
      "distance": 131.47789999999998,
      "hours": 0.3275957957957958,
      "clubPoints": 1.7687602462462464,
      "elevation": 2324.6000000000004
    }
  ]
}