{
  "timestamp": 1677176803,
  "totalData": {
    "totalDistance": 1124.0953666666665,
    "totalHours": 600.0999999999998,
    "totalPoints": 17.498278490884314
  },
  "summary": [
    {
      "name": "Nordic Semiconductor - Finland",
      "distance": 190.5669,
      "hours": 0.4524374021909233,
      "clubPoints": 2.684040845070423,
      "elevation": 3262.5
    },
    {
      "name": "Nordic Semiconductor - Poland",
      "distance": 169.71030000000002,
      "hours": 0.9254662698412699,
      "clubPoints": 6.061082142857142,
      "elevation": 1501.1
    },
    {
      "name": "Nordic Semiconductor - Europe",
      "distance": 148.9785,
      "hours": 0.3586583924349882,
      "clubPoints": 3.1697553191489356,
      "elevation": 1034.3
    },
    {
      "name": "Nordic Semiconductor - APAC",
      "distance": 54.90520000000001,
      "hours": 0.1340923317683881,
      "clubPoints": 0.7733126760563381,
      "elevation": 614.6999999999999
    },
    {
      "name": "Nordic Semiconductor - USA",
      "distance": 37.407500000000006,
      "hours": 0.49597222222222215,
      "clubPoints": 1.8703750000000001,
      "elevation": 602.5000000000001
    },
    {
      "name": "Nordic Semiconductor - Trondheim Office",
      "distance": 177.21336666666662,
      "hours": 0.3278500986193294,
      "clubPoints": 1.048599802761341,
      "elevation": 8580.100000000002
    },
    {
      "name": "Omega NTNU",
      "distance": 272.7,
      "hours": 1.4272942655619891,
      "clubPoints": 0.9356705997269689,
      "elevation": 2114.6
    },
    {
      "name": "Nordic Semiconductor - Oslo Office",
      "distance": 72.6136,
      "hours": 0.4427960526315789,
      "clubPoints": 0.9554421052631578,
      "elevation": 2734.4
    }
  ]
}