{
  "timestamp": 1663918859,
  "totalData": {
    "totalDistance": 1915.5389799999998,
    "totalHours": 323.9458333333335,
    "totalPoints": 25.28957854530508
  },
  "summary": [
    {
      "name": "Nordic Semiconductor - Finland",
      "distance": 359.53848,
      "hours": 0.9345768157648813,
      "clubPoints": 5.34959745621848,
      "elevation": 3251.6999999999994
    },
    {
      "name": "Nordic Semiconductor - Poland",
      "distance": 95.3377,
      "hours": 0.6460670194003526,
      "clubPoints": 3.462002160493827,
      "elevation": 1472.6999999999998
    },
    {
      "name": "Nordic Semiconductor - Europe",
      "distance": 133.7204,
      "hours": 0.4470597643097643,
      "clubPoints": 3.0067684175084177,
      "elevation": 826.5000000000001
    },
    {
      "name": "Nordic Semiconductor - APAC",
      "distance": 109.8365,
      "hours": 0.33590091843230896,
      "clubPoints": 1.7537755780535476,
      "elevation": 1199.6000000000001
    },
    {
      "name": "Nordic Semiconductor - USA",
      "distance": 102.25763333333332,
      "hours": 1.3615392015392016,
      "clubPoints": 4.772181457431457,
      "elevation": 1250.9
    },
    {
      "name": "Nordic Semiconductor - Trondheim Office",
      "distance": 378.65006666666676,
      "hours": 0.36909056072476737,
      "clubPoints": 2.3607895587824594,
      "elevation": 6175.300000000001
    },
    {
      "name": "Omega NTNU",
      "distance": 511.7271999999999,
      "hours": 0.20329003943877913,
      "clubPoints": 1.7096132060656497,
      "elevation": 8245.8
    },
    {
      "name": "Nordic Semiconductor - Oslo Office",
      "distance": 224.471,
      "hours": 0.6912449696660224,
      "clubPoints": 2.9748507107512374,
      "elevation": 3863.8000000000006
    }
  ]
}