{
  "timestamp": 1678292982,
  "totalData": {
    "totalDistance": 951.8590866666668,
    "totalHours": 166.38194444444434,
    "totalPoints": 13.302609856235978
  },
  "summary": [
    {
      "name": "Nordic Semiconductor - Finland",
      "distance": 166.48195333333334,
      "hours": 0.4923630672926448,
      "clubPoints": 2.344816244131455,
      "elevation": 2674.8
    },
    {
      "name": "Nordic Semiconductor - Poland",
      "distance": 100.43216666666667,
      "hours": 0.5385317460317459,
      "clubPoints": 3.5868630952380953,
      "elevation": 796.3
    },
    {
      "name": "Nordic Semiconductor - Europe",
      "distance": 27.679,
      "hours": 0.0836820330969267,
      "clubPoints": 0.5889148936170212,
      "elevation": 250.20000000000002
    },
    {
      "name": "Nordic Semiconductor - APAC",
      "distance": 49.8565,
      "hours": 0.09820031298904539,
      "clubPoints": 0.7022042253521127,
      "elevation": 246.49999999999997
    },
    {
      "name": "Nordic Semiconductor - USA",
      "distance": 64.49426666666668,
      "hours": 0.8313750000000001,
      "clubPoints": 3.2247133333333338,
      "elevation": 11029.5
    },
    {
      "name": "Nordic Semiconductor - Trondheim Office",
      "distance": 160.2885,
      "hours": 0.2288264299802762,
      "clubPoints": 0.9484526627218934,
      "elevation": 3309
    },
    {
      "name": "Omega NTNU",
      "distance": 321.18260000000004,
      "hours": 0.12272598908577097,
      "clubPoints": 1.0981704018420684,
      "elevation": 3290
    },
    {
      "name": "Nordic Semiconductor - Oslo Office",
      "distance": 61.444100000000006,
      "hours": 0.1873720760233918,
      "clubPoints": 0.8084749999999999,
      "elevation": 1267.9
    }
  ]
}