{
  "timestamp": 1667291581,
  "totalData": {
    "totalDistance": 519.8747666666667,
    "totalHours": 88.55055555555555,
    "totalPoints": 7.531900864419797
  },
  "summary": [
    {
      "name": "Nordic Semiconductor - Finland",
      "distance": 41.776133333333334,
      "hours": 0.156195987654321,
      "clubPoints": 0.580224074074074,
      "elevation": 499.29999999999995
    },
    {
      "name": "Nordic Semiconductor - Poland",
      "distance": 92.74253333333334,
      "hours": 0.6807142857142858,
      "clubPoints": 3.3122333333333334,
      "elevation": 2552.3
    },
    {
      "name": "Nordic Semiconductor - Europe",
      "distance": 55.159,
      "hours": 0.2921749408983451,
      "clubPoints": 1.1735957446808511,
      "elevation": 2077.3
    },
    {
      "name": "Nordic Semiconductor - APAC",
      "distance": 18.8715,
      "hours": 0.04793981481481481,
      "clubPoints": 0.2621041666666667,
      "elevation": 2.7
    },
    {
      "name": "Nordic Semiconductor - USA",
      "distance": 19.737066666666664,
      "hours": 0.09133597883597884,
      "clubPoints": 0.9398603174603175,
      "elevation": 154.9
    },
    {
      "name": "Nordic Semiconductor - Trondheim Office",
      "distance": 75.78693333333334,
      "hours": 0.08244904667981591,
      "clubPoints": 0.4484433925049309,
      "elevation": 901.5
    },
    {
      "name": "Omega NTNU",
      "distance": 207.7869,
      "hours": 0.07348151762847988,
      "clubPoints": 0.7113528227126092,
      "elevation": 1948.6999999999998
    },
    {
      "name": "Nordic Semiconductor - Oslo Office",
      "distance": 8.014700000000001,
      "hours": 0.048639971139971136,
      "clubPoints": 0.10408701298701299,
      "elevation": 203.3
    }
  ]
}