{
  "timestamp": 1664292685,
  "totalData": {
    "totalDistance": 702.3190466666666,
    "totalHours": 133.17055555555555,
    "totalPoints": 9.432727725219177
  },
  "summary": [
    {
      "name": "Nordic Semiconductor - Finland",
      "distance": 205.8981333333333,
      "hours": 0.4823547178130511,
      "clubPoints": 2.9319441666666672,
      "elevation": 2008.8
    },
    {
      "name": "Nordic Semiconductor - Poland",
      "distance": 50.95146666666667,
      "hours": 0.4101388888888888,
      "clubPoints": 1.8196952380952383,
      "elevation": 1065
    },
    {
      "name": "Nordic Semiconductor - Europe",
      "distance": 41.12733333333333,
      "hours": 0.12356691919191919,
      "clubPoints": 0.9347121212121211,
      "elevation": 292.8
    },
    {
      "name": "Nordic Semiconductor - APAC",
      "distance": 31.215200000000003,
      "hours": 0.23707711442786067,
      "clubPoints": 0.46589850746268663,
      "elevation": 839.3
    },
    {
      "name": "Nordic Semiconductor - USA",
      "distance": 28.433533333333337,
      "hours": 0.4653306878306879,
      "clubPoints": 1.3539777777777777,
      "elevation": 496.00000000000006
    },
    {
      "name": "Nordic Semiconductor - Trondheim Office",
      "distance": 99.44131333333333,
      "hours": 0.10553523035230353,
      "clubPoints": 0.6063494715447155,
      "elevation": 1152.9
    },
    {
      "name": "Omega NTNU",
      "distance": 193.276,
      "hours": 0.06772810712223797,
      "clubPoints": 0.6622255479452055,
      "elevation": 1841.6999999999998
    },
    {
      "name": "Nordic Semiconductor - Oslo Office",
      "distance": 51.976066666666675,
      "hours": 0.24888185654008438,
      "clubPoints": 0.6579248945147679,
      "elevation": 852.5000000000001
    }
  ]
}