{
  "timestamp": 1681489469,
  "totalData": {
    "totalDistance": 2066.7879666666668,
    "totalHours": 322.0375,
    "totalPoints": 25.202163025039262
  },
  "summary": [
    {
      "name": "Nordic Semiconductor - Finland",
      "distance": 351.33299999999997,
      "hours": 0.9242671178586673,
      "clubPoints": 4.886389427473934,
      "elevation": 8630.300000000001
    },
    {
      "name": "Nordic Semiconductor - Poland",
      "distance": 168.10656666666668,
      "hours": 0.8195634920634921,
      "clubPoints": 6.003805952380953,
      "elevation": 2853.6
    },
    {
      "name": "Nordic Semiconductor - Europe",
      "distance": 77.38016666666667,
      "hours": 0.2083274231678487,
      "clubPoints": 1.6463865248226948,
      "elevation": 815.8
    },
    {
      "name": "Nordic Semiconductor - APAC",
      "distance": 58.96350000000001,
      "hours": 0.1285099485803711,
      "clubPoints": 0.8169389995731967,
      "elevation": 449.5
    },
    {
      "name": "Nordic Semiconductor - USA",
      "distance": 112.13663333333335,
      "hours": 1.1275972222222224,
      "clubPoints": 5.606831666666666,
      "elevation": 4221.799999999999
    },
    {
      "name": "Nordic Semiconductor - Trondheim Office",
      "distance": 387.12923333333333,
      "hours": 0.4480115978444466,
      "clubPoints": 2.301013948244907,
      "elevation": 9095.600000000002
    },
    {
      "name": "Omega NTNU",
      "distance": 827.0581999999997,
      "hours": 0.3418002053094732,
      "clubPoints": 2.829239596558152,
      "elevation": 11240.199999999997
    },
    {
      "name": "Nordic Semiconductor - Oslo Office",
      "distance": 84.68066666666665,
      "hours": 0.2075304739120529,
      "clubPoints": 1.1115569093187514,
      "elevation": 1412.4
    }
  ]
}