{
  "timestamp": 1692184465,
  "totalData": {
    "totalDistance": 1165.5086333333331,
    "totalHours": 200.81500000000003,
    "totalPoints": 12.113550280296165
  },
  "summary": [
    {
      "name": "Nordic Semiconductor - Finland",
      "distance": 263.2695666666666,
      "hours": 0.5065520833333332,
      "clubPoints": 3.2908695833333335,
      "elevation": 3434.6000000000004
    },
    {
      "name": "Nordic Semiconductor - Poland",
      "distance": 92.74053333333332,
      "hours": 1.0114980158730158,
      "clubPoints": 3.3121619047619046,
      "elevation": 1250.6999999999998
    },
    {
      "name": "Nordic Semiconductor - Europe",
      "distance": 42.65406666666667,
      "hours": 0.34617400419287214,
      "clubPoints": 0.8047937106918238,
      "elevation": 445.70000000000005
    },
    {
      "name": "Nordic Semiconductor - APAC",
      "distance": 62.67236666666666,
      "hours": 0.11366666666666667,
      "clubPoints": 0.7834045833333333,
      "elevation": 491
    },
    {
      "name": "Nordic Semiconductor - USA",
      "distance": 12.2954,
      "hours": 0.1870138888888889,
      "clubPoints": 0.61477,
      "elevation": 176.9
    },
    {
      "name": "Nordic Semiconductor - Trondheim Office",
      "distance": 204.6272,
      "hours": 0.22935944140862174,
      "clubPoints": 1.1181814207650271,
      "elevation": 3955.4
    },
    {
      "name": "Omega NTNU",
      "distance": 421.50610000000006,
      "hours": 0.12734482167352534,
      "clubPoints": 1.30094475308642,
      "elevation": 6352.5
    },
    {
      "name": "Nordic Semiconductor - Oslo Office",
      "distance": 65.74340000000001,
      "hours": 0.23723723723723725,
      "clubPoints": 0.8884243243243244,
      "elevation": 1465.6000000000001
    }
  ]
}