{
  "timestamp": 1684031728,
  "totalData": {
    "totalDistance": 4962.708853333335,
    "totalHours": 878.8927777777781,
    "totalPoints": 59.91190773016082
  },
  "summary": [
    {
      "name": "Nordic Semiconductor - Finland",
      "distance": 1047.1358599999999,
      "hours": 2.005739583333334,
      "clubPoints": 13.089198250000003,
      "elevation": 16959.3
    },
    {
      "name": "Nordic Semiconductor - Poland",
      "distance": 323.46666666666664,
      "hours": 3.8455158730158736,
      "clubPoints": 11.55238095238095,
      "elevation": 4966.500000000001
    },
    {
      "name": "Nordic Semiconductor - Europe",
      "distance": 276.48986666666667,
      "hours": 1.594014675052411,
      "clubPoints": 5.216789937106918,
      "elevation": 2935.4
    },
    {
      "name": "Nordic Semiconductor - APAC",
      "distance": 420.68469999999985,
      "hours": 1.0912207218792869,
      "clubPoints": 5.19506686728395,
      "elevation": 6840.399999999999
    },
    {
      "name": "Nordic Semiconductor - USA",
      "distance": 192.4414666666667,
      "hours": 2.7389583333333336,
      "clubPoints": 9.622073333333333,
      "elevation": 4208.200000000001
    },
    {
      "name": "Nordic Semiconductor - Trondheim Office",
      "distance": 924.1179600000003,
      "hours": 0.807970552519733,
      "clubPoints": 5.049824918032785,
      "elevation": 20286.699999999993
    },
    {
      "name": "Omega NTNU",
      "distance": 1305.8208000000006,
      "hours": 0.4318022491223798,
      "clubPoints": 4.045748337595908,
      "elevation": 15456.699999999999
    },
    {
      "name": "Nordic Semiconductor - Oslo Office",
      "distance": 472.5515333333334,
      "hours": 1.246260395306448,
      "clubPoints": 6.140825134426976,
      "elevation": 9989.999999999998
    }
  ]
}