{
  "timestamp": 1678991146,
  "totalData": {
    "totalDistance": 45.5017,
    "totalHours": 8.432222222222222,
    "totalPoints": 1.2068149026096655
  },
  "summary": [
    {
      "name": "Nordic Semiconductor - Finland",
      "distance": 0,
      "hours": 0,
      "clubPoints": 0,
      "elevation": 0
    },
    {
      "name": "Nordic Semiconductor - Poland",
      "distance": 22.523600000000002,
      "hours": 0.11916666666666667,
      "clubPoints": 0.8044142857142857,
      "elevation": 189.7
    },
    {
      "name": "Nordic Semiconductor - Europe",
      "distance": 17.3467,
      "hours": 0.055892434988179675,
      "clubPoints": 0.3690787234042553,
      "elevation": 132.60000000000002
    },
    {
      "name": "Nordic Semiconductor - APAC",
      "distance": 0,
      "hours": 0,
      "clubPoints": 0,
      "elevation": 0
    },
    {
      "name": "Nordic Semiconductor - USA",
      "distance": 0,
      "hours": 0,
      "clubPoints": 0,
      "elevation": 0
    },
    {
      "name": "Nordic Semiconductor - Trondheim Office",
      "distance": 5.631399999999999,
      "hours": 0.014607166337935568,
      "clubPoints": 0.03332189349112426,
      "elevation": 174.3
    },
    {
      "name": "Omega NTNU",
      "distance": 0,
      "hours": 0,
      "clubPoints": 0,
      "elevation": 0
    },
    {
      "name": "Nordic Semiconductor - Oslo Office",
      "distance": 0,
      "hours": 0,
      "clubPoints": 0,
      "elevation": 0
    }
  ]
}