{
  "timestamp": 1680762193,
  "totalData": {
    "totalDistance": 14.249600000000001,
    "totalHours": 1.9033333333333333,
    "totalPoints": 0.23951049378462558
  },
  "summary": [
    {
      "name": "Nordic Semiconductor - Finland",
      "distance": 2.7451,
      "hours": 0.006349765258215963,
      "clubPoints": 0.03866338028169014,
      "elevation": 48
    },
    {
      "name": "Nordic Semiconductor - Poland",
      "distance": 5,
      "hours": 0.025416666666666667,
      "clubPoints": 0.17857142857142858,
      "elevation": 0
    },
    {
      "name": "Nordic Semiconductor - Europe",
      "distance": 0,
      "hours": 0,
      "clubPoints": 0,
      "elevation": 0
    },
    {
      "name": "Nordic Semiconductor - APAC",
      "distance": 0,
      "hours": 0,
      "clubPoints": 0,
      "elevation": 0
    },
    {
      "name": "Nordic Semiconductor - USA",
      "distance": 0,
      "hours": 0,
      "clubPoints": 0,
      "elevation": 0
    },
    {
      "name": "Nordic Semiconductor - Trondheim Office",
      "distance": 0,
      "hours": 0,
      "clubPoints": 0,
      "elevation": 0
    },
    {
      "name": "Omega NTNU",
      "distance": 6.5045,
      "hours": 0.0025371004566210045,
      "clubPoints": 0.02227568493150685,
      "elevation": 0
    },
    {
      "name": "Nordic Semiconductor - Oslo Office",
      "distance": 0,
      "hours": 0,
      "clubPoints": 0,
      "elevation": 0
    }
  ]
}