{
  "timestamp": 1678036648,
  "totalData": {
    "totalDistance": 16.2669,
    "totalHours": 4.407222222222222,
    "totalPoints": 0.15152248418412423
  },
  "summary": [
    {
      "name": "Nordic Semiconductor - Finland",
      "distance": 1.4558,
      "hours": 0.009718309859154929,
      "clubPoints": 0.020504225352112677,
      "elevation": 31.7
    },
    {
      "name": "Nordic Semiconductor - Poland",
      "distance": 0,
      "hours": 0,
      "clubPoints": 0,
      "elevation": 0
    },
    {
      "name": "Nordic Semiconductor - Europe",
      "distance": 0,
      "hours": 0,
      "clubPoints": 0,
      "elevation": 0
    },
    {
      "name": "Nordic Semiconductor - APAC",
      "distance": 0,
      "hours": 0,
      "clubPoints": 0,
      "elevation": 0
    },
    {
      "name": "Nordic Semiconductor - USA",
      "distance": 0,
      "hours": 0,
      "clubPoints": 0,
      "elevation": 0
    },
    {
      "name": "Nordic Semiconductor - Trondheim Office",
      "distance": 0,
      "hours": 0,
      "clubPoints": 0,
      "elevation": 0
    },
    {
      "name": "Omega NTNU",
      "distance": 6.5615,
      "hours": 0.002022450532724505,
      "clubPoints": 0.022470890410958903,
      "elevation": 49.1
    },
    {
      "name": "Nordic Semiconductor - Oslo Office",
      "distance": 8.249600000000001,
      "hours": 0.041140350877192984,
      "clubPoints": 0.10854736842105264,
      "elevation": 153.5
    }
  ]
}