{
  "timestamp": 1686176228,
  "totalData": {
    "totalDistance": 28.868899999999996,
    "totalHours": 2.8641666666666667,
    "totalPoints": 0.3873988012939478
  },
  "summary": [
    {
      "name": "Nordic Semiconductor - Finland",
      "distance": 0,
      "hours": 0,
      "clubPoints": 0,
      "elevation": 0
    },
    {
      "name": "Nordic Semiconductor - Poland",
      "distance": 0,
      "hours": 0,
      "clubPoints": 0,
      "elevation": 0
    },
    {
      "name": "Nordic Semiconductor - Europe",
      "distance": 15.2205,
      "hours": 0.025157232704402514,
      "clubPoints": 0.28717924528301886,
      "elevation": 0
    },
    {
      "name": "Nordic Semiconductor - APAC",
      "distance": 3.6441,
      "hours": 0.006701388888888889,
      "clubPoints": 0.04555125,
      "elevation": 52
    },
    {
      "name": "Nordic Semiconductor - USA",
      "distance": 0,
      "hours": 0,
      "clubPoints": 0,
      "elevation": 0
    },
    {
      "name": "Nordic Semiconductor - Trondheim Office",
      "distance": 10.004299999999999,
      "hours": 0.005435640558591378,
      "clubPoints": 0.05466830601092896,
      "elevation": 174
    },
    {
      "name": "Omega NTNU",
      "distance": 0,
      "hours": 0,
      "clubPoints": 0,
      "elevation": 0
    },
    {
      "name": "Nordic Semiconductor - Oslo Office",
      "distance": 0,
      "hours": 0,
      "clubPoints": 0,
      "elevation": 0
    }
  ]
}