{
  "timestamp": 1691396563,
  "totalData": {
    "totalDistance": 7.6911000000000005,
    "totalHours": 1.4547222222222222,
    "totalPoints": 0.1713414285714286
  },
  "summary": [
    {
      "name": "Nordic Semiconductor - Finland",
      "distance": 4.4516,
      "hours": 0.006625000000000001,
      "clubPoints": 0.055645,
      "elevation": 31.1
    },
    {
      "name": "Nordic Semiconductor - Poland",
      "distance": 3.2395,
      "hours": 0.03302579365079365,
      "clubPoints": 0.11569642857142858,
      "elevation": 42
    },
    {
      "name": "Nordic Semiconductor - Europe",
      "distance": 0,
      "hours": 0,
      "clubPoints": 0,
      "elevation": 0
    },
    {
      "name": "Nordic Semiconductor - APAC",
      "distance": 0,
      "hours": 0,
      "clubPoints": 0,
      "elevation": 0
    },
    {
      "name": "Nordic Semiconductor - USA",
      "distance": 0,
      "hours": 0,
      "clubPoints": 0,
      "elevation": 0
    },
    {
      "name": "Nordic Semiconductor - Trondheim Office",
      "distance": 0,
      "hours": 0,
      "clubPoints": 0,
      "elevation": 0
    },
    {
      "name": "Omega NTNU",
      "distance": 0,
      "hours": 0,
      "clubPoints": 0,
      "elevation": 0
    },
    {
      "name": "Nordic Semiconductor - Oslo Office",
      "distance": 0,
      "hours": 0,
      "clubPoints": 0,
      "elevation": 0
    }
  ]
}