{
  "timestamp": 1679980703,
  "totalData": {
    "totalDistance": 6.948833333333333,
    "totalHours": 1.3263888888888888,
    "totalPoints": 0.14383500281769515
  },
  "summary": [
    {
      "name": "Nordic Semiconductor - Finland",
      "distance": 0,
      "hours": 0,
      "clubPoints": 0,
      "elevation": 0
    },
    {
      "name": "Nordic Semiconductor - Poland",
      "distance": 3.4472333333333336,
      "hours": 0.022291666666666664,
      "clubPoints": 0.1231154761904762,
      "elevation": 33
    },
    {
      "name": "Nordic Semiconductor - Europe",
      "distance": 0,
      "hours": 0,
      "clubPoints": 0,
      "elevation": 0
    },
    {
      "name": "Nordic Semiconductor - APAC",
      "distance": 0,
      "hours": 0,
      "clubPoints": 0,
      "elevation": 0
    },
    {
      "name": "Nordic Semiconductor - USA",
      "distance": 0,
      "hours": 0,
      "clubPoints": 0,
      "elevation": 0
    },
    {
      "name": "Nordic Semiconductor - Trondheim Office",
      "distance": 3.5016,
      "hours": 0.004155161078238001,
      "clubPoints": 0.020719526627218935,
      "elevation": 57.7
    },
    {
      "name": "Omega NTNU",
      "distance": 0,
      "hours": 0,
      "clubPoints": 0,
      "elevation": 0
    },
    {
      "name": "Nordic Semiconductor - Oslo Office",
      "distance": 0,
      "hours": 0,
      "clubPoints": 0,
      "elevation": 0
    }
  ]
}