{
  "timestamp": 1683026125,
  "totalData": {
    "totalDistance": 17.5182,
    "totalHours": 2.653888888888889,
    "totalPoints": 0.1147383468115352
  },
  "summary": [
    {
      "name": "Nordic Semiconductor - Finland",
      "distance": 0,
      "hours": 0,
      "clubPoints": 0,
      "elevation": 0
    },
    {
      "name": "Nordic Semiconductor - Poland",
      "distance": 0,
      "hours": 0,
      "clubPoints": 0,
      "elevation": 0
    },
    {
      "name": "Nordic Semiconductor - Europe",
      "distance": 0,
      "hours": 0,
      "clubPoints": 0,
      "elevation": 0
    },
    {
      "name": "Nordic Semiconductor - APAC",
      "distance": 5.2368999999999994,
      "hours": 0.016694101508916325,
      "clubPoints": 0.06465308641975308,
      "elevation": 34.7
    },
    {
      "name": "Nordic Semiconductor - USA",
      "distance": 0,
      "hours": 0,
      "clubPoints": 0,
      "elevation": 0
    },
    {
      "name": "Nordic Semiconductor - Trondheim Office",
      "distance": 5,
      "hours": 0.0022893772893772895,
      "clubPoints": 0.027472527472527472,
      "elevation": 0
    },
    {
      "name": "Omega NTNU",
      "distance": 7.2813,
      "hours": 0.002748447204968944,
      "clubPoints": 0.02261273291925466,
      "elevation": 0
    },
    {
      "name": "Nordic Semiconductor - Oslo Office",
      "distance": 0,
      "hours": 0,
      "clubPoints": 0,
      "elevation": 0
    }
  ]
}