{
  "timestamp": 1683102156,
  "totalData": {
    "totalDistance": 18.0533,
    "totalHours": 2.1827777777777775,
    "totalPoints": 0.1924851244133743
  },
  "summary": [
    {
      "name": "Nordic Semiconductor - Finland",
      "distance": 6.8206999999999995,
      "hours": 0.010784722222222222,
      "clubPoints": 0.08525875,
      "elevation": 93
    },
    {
      "name": "Nordic Semiconductor - Poland",
      "distance": 0,
      "hours": 0,
      "clubPoints": 0,
      "elevation": 0
    },
    {
      "name": "Nordic Semiconductor - Europe",
      "distance": 2.8196999999999997,
      "hours": 0.004376310272536687,
      "clubPoints": 0.05320188679245282,
      "elevation": 26
    },
    {
      "name": "Nordic Semiconductor - APAC",
      "distance": 0,
      "hours": 0,
      "clubPoints": 0,
      "elevation": 0
    },
    {
      "name": "Nordic Semiconductor - USA",
      "distance": 0,
      "hours": 0,
      "clubPoints": 0,
      "elevation": 0
    },
    {
      "name": "Nordic Semiconductor - Trondheim Office",
      "distance": 0,
      "hours": 0,
      "clubPoints": 0,
      "elevation": 0
    },
    {
      "name": "Omega NTNU",
      "distance": 5.6431000000000004,
      "hours": 0.0015948425060574594,
      "clubPoints": 0.0175797507788162,
      "elevation": 54
    },
    {
      "name": "Nordic Semiconductor - Oslo Office",
      "distance": 2.7697999999999996,
      "hours": 0.007580409356725147,
      "clubPoints": 0.03644473684210526,
      "elevation": 89
    }
  ]
}