{
  "timestamp": 1662808907,
  "totalData": {
    "totalDistance": 71,
    "totalHours": 12,
    "totalPoints": 0.4
  },
  "summary": [
    {
      "name": "Nordic Semiconductor - Finland",
      "distance": 0,
      "hours": 0,
      "clubPoints": 0,
      "elevation": 0
    },
    {
      "name": "Nordic Semiconductor - Poland",
      "distance": 0,
      "hours": 0,
      "clubPoints": 0,
      "elevation": 0
    },
    {
      "name": "Nordic Semiconductor - Europe",
      "distance": 0,
      "hours": 0,
      "clubPoints": 0,
      "elevation": 0
    },
    {
      "name": "Nordic Semiconductor - APAC",
      "distance": 9.4,
      "hours": 1.2,
      "clubPoints": 0.2,
      "elevation": 240.3
    },
    {
      "name": "Nordic Semiconductor - USA",
      "distance": 0,
      "hours": 0,
      "clubPoints": 0,
      "elevation": 0
    },
    {
      "name": "Nordic Semiconductor - Trondheim Office",
      "distance": 6.8,
      "hours": 2.7,
      "clubPoints": 0,
      "elevation": 480
    },
    {
      "name": "Omega NTNU",
      "distance": 54.8,
      "hours": 8.1,
      "clubPoints": 0.2,
      "elevation": 1764.8
    },
    {
      "name": "Nordic Semiconductor - Oslo Office",
      "distance": 0,
      "hours": 0,
      "clubPoints": 0,
      "elevation": 0
    }
  ]
}