{
  "timestamp": 1671481322,
  "totalData": {
    "totalDistance": 24.357499999999998,
    "totalHours": 5.864444444444445,
    "totalPoints": 0.15167510101520562
  },
  "summary": [
    {
      "name": "Nordic Semiconductor - Finland",
      "distance": 3.5777666666666663,
      "hours": 0.04258873456790123,
      "clubPoints": 0.049691203703703696,
      "elevation": 37.4
    },
    {
      "name": "Nordic Semiconductor - Poland",
      "distance": 0,
      "hours": 0,
      "clubPoints": 0,
      "elevation": 0
    },
    {
      "name": "Nordic Semiconductor - Europe",
      "distance": 0,
      "hours": 0,
      "clubPoints": 0,
      "elevation": 0
    },
    {
      "name": "Nordic Semiconductor - APAC",
      "distance": 0,
      "hours": 0,
      "clubPoints": 0,
      "elevation": 0
    },
    {
      "name": "Nordic Semiconductor - USA",
      "distance": 0,
      "hours": 0,
      "clubPoints": 0,
      "elevation": 0
    },
    {
      "name": "Nordic Semiconductor - Trondheim Office",
      "distance": 12.500733333333333,
      "hours": 0.007415032679738562,
      "clubPoints": 0.07353372549019607,
      "elevation": 44
    },
    {
      "name": "Omega NTNU",
      "distance": 8.279,
      "hours": 0.005283505154639176,
      "clubPoints": 0.028450171821305843,
      "elevation": 7.3
    },
    {
      "name": "Nordic Semiconductor - Oslo Office",
      "distance": 0,
      "hours": 0,
      "clubPoints": 0,
      "elevation": 0
    }
  ]
}